libname/__init__.py
libname/csv_loader_simplified.py
libname/main.py
libname/printer.py
semanticlatex-0.0.1.dist-info/LICENSE.md
semanticlatex-0.0.1.dist-info/METADATA
semanticlatex-0.0.1.dist-info/WHEEL
semanticlatex-0.0.1.dist-info/top_level.txt
semanticlatex-0.0.1.dist-info/RECORD
