Metadata-Version: 2.1
Name: semanticlatex
Version: 0.0.1
Summary: Translating a sympy expression to its latex equivalent.
Author: Dariokula
Author-email: <dario.kulaszewski@web.de>
Keywords: python,latex,sympy,sockets
Classifier: Development Status :: 4 - Beta
Classifier: Intended Audience :: Developers
Classifier: Programming Language :: Python :: 3
Classifier: Operating System :: Unix
Classifier: Operating System :: MacOS :: MacOS X
Classifier: Operating System :: Microsoft :: Windows
License-File: LICENSE.md
